xlwings_mcp/__init__.py
xlwings_mcp/server.py
xlwings_mcp-0.1.1.dist-info/METADATA
xlwings_mcp-0.1.1.dist-info/WHEEL
xlwings_mcp-0.1.1.dist-info/entry_points.txt
xlwings_mcp-0.1.1.dist-info/RECORD
